everyconfig/__init__.py
everyconfig-1.0.3.dist-info/RECORD
everyconfig-1.0.3.dist-info/WHEEL
everyconfig-1.0.3.dist-info/metadata.json
everyconfig-1.0.3.dist-info/top_level.txt
everyconfig-1.0.3.dist-info/METADATA
everyconfig-1.0.3.dist-info/DESCRIPTION.rst
