Metadata-Version: 2.0
Name: everyconfig
Version: 1.0.3
Summary: use the same .yaml config files in every language
Home-page: https://github.com/pbrandt1/everyconfig
Author: Peter Brandt
Author-email: peter.m.brandt@gmail.com
License: MIT
Keywords: configuration,configuration management,environment
Platform: UNKNOWN
Classifier: Development Status :: 5 - Production/Stable
Classifier: Intended Audience :: Developers
Classifier: Topic :: Utilities
Classifier: License :: OSI Approved :: MIT License
Classifier: Programming Language :: Python :: 2.7
Requires-Dist: pyyaml
Requires-Dist: easydict
